anthillpy/__init__.py
anthillpy/anthillpy.py
anthillpy/mock.json
anthillpy/test.py
anthillpy-1.0.1.dist-info/METADATA
anthillpy-1.0.1.dist-info/WHEEL
anthillpy-1.0.1.dist-info/top_level.txt
anthillpy-1.0.1.dist-info/RECORD
